{
  "hash": "bad8213d",
  "configHash": "061293f4",
  "lockfileHash": "f8777c69",
  "browserHash": "49f5eabc",
  "optimized": {
    "vue": {
      "src": "../../../../node_modules/vue/dist/vue.runtime.esm-bundler.js",
      "file": "vue.js",
      "fileHash": "8e2ed5ba",
      "needsInterop": false
    },
    "vitepress > @vue/devtools-api": {
      "src": "../../../../node_modules/@vue/devtools-api/dist/index.js",
      "file": "vitepress___@vue_devtools-api.js",
      "fileHash": "ad72faf0",
      "needsInterop": false
    },
    "vitepress > @vueuse/core": {
      "src": "../../../../node_modules/@vueuse/core/index.mjs",
      "file": "vitepress___@vueuse_core.js",
      "fileHash": "7e5564b7",
      "needsInterop": false
    },
    "vitepress > @vueuse/integrations/useFocusTrap": {
      "src": "../../../../node_modules/@vueuse/integrations/useFocusTrap.mjs",
      "file": "vitepress___@vueuse_integrations_useFocusTrap.js",
      "fileHash": "50fd8033",
      "needsInterop": false
    },
    "vitepress > mark.js/src/vanilla.js": {
      "src": "../../../../node_modules/mark.js/src/vanilla.js",
      "file": "vitepress___mark__js_src_vanilla__js.js",
      "fileHash": "b1769d55",
      "needsInterop": false
    },
    "vitepress > minisearch": {
      "src": "../../../../node_modules/minisearch/dist/es/index.js",
      "file": "vitepress___minisearch.js",
      "fileHash": "4cdfea96",
      "needsInterop": false
    }
  },
  "chunks": {
    "chunk-2CGNBZMC": {
      "file": "chunk-2CGNBZMC.js"
    },
    "chunk-NPGVKGNX": {
      "file": "chunk-NPGVKGNX.js"
    }
  }
}